<?xml version="1.0" encoding="UTF-8"?>
<export version="D">
  <design>
    <source>/Users/tjcampie/Documents/Keyboards/Adalyn/PCB/Adalyn.sch</source>
    <date>Wednesday, November 17, 2021 at 07:58:33 PM</date>
    <tool>Eeschema (5.1.10-1-10_14)</tool>
    <sheet number="1" name="/" tstamps="/">
      <title_block>
        <title/>
        <company/>
        <rev/>
        <date/>
        <source>Adalyn.sch</source>
        <comment number="1" value=""/>
        <comment number="2" value=""/>
        <comment number="3" value=""/>
        <comment number="4" value=""/>
      </title_block>
    </sheet>
  </design>
  <components>
    <comp ref="MX1">
      <value>MX-NoLED</value>
      <footprint>MX_Only:MXOnly-1U-NoLED</footprint>
      <libsource lib="MX_Alps_Hybrid" part="MX-NoLED" description=""/>
      <sheetpath names="/" tstamps="/"/>
      <tstamp>5F0B91BC</tstamp>
    </comp>
    <comp ref="MX7">
      <value>MX-NoLED</value>
      <footprint>MX_Only:MXOnly-1U-NoLED</footprint>
      <libsource lib="MX_Alps_Hybrid" part="MX-NoLED" description=""/>
      <sheetpath names="/" tstamps="/"/>
      <tstamp>5F0F7B30</tstamp>
    </comp>
    <comp ref="MX11">
      <value>MX-NoLED</value>
      <footprint>MX_Only:MXOnly-1U-NoLED</footprint>
      <libsource lib="MX_Alps_Hybrid" part="MX-NoLED" description=""/>
      <sheetpath names="/" tstamps="/"/>
      <tstamp>5F0F7B3F</tstamp>
    </comp>
    <comp ref="MX16">
      <value>MX-NoLED</value>
      <footprint>MX_Only:MXOnly-1U-NoLED</footprint>
      <libsource lib="MX_Alps_Hybrid" part="MX-NoLED" description=""/>
      <sheetpath names="/" tstamps="/"/>
      <tstamp>5F0FE19A</tstamp>
    </comp>
    <comp ref="MX20">
      <value>MX-NoLED</value>
      <footprint>MX_Only:MXOnly-1U-NoLED</footprint>
      <libsource lib="MX_Alps_Hybrid" part="MX-NoLED" description=""/>
      <sheetpath names="/" tstamps="/"/>
      <tstamp>5F0FE1A9</tstamp>
    </comp>
    <comp ref="MX23">
      <value>MX-NoLED</value>
      <footprint>MX_Only:MXOnly-1U-NoLED</footprint>
      <libsource lib="MX_Alps_Hybrid" part="MX-NoLED" description=""/>
      <sheetpath names="/" tstamps="/"/>
      <tstamp>5F0FE1B8</tstamp>
    </comp>
    <comp ref="MX27">
      <value>MX-NoLED</value>
      <footprint>MX_Only:MXOnly-1U-NoLED</footprint>
      <libsource lib="MX_Alps_Hybrid" part="MX-NoLED" description=""/>
      <sheetpath names="/" tstamps="/"/>
      <tstamp>5F0FE1C7</tstamp>
    </comp>
    <comp ref="MX32">
      <value>MX-NoLED</value>
      <footprint>MX_Only:MXOnly-1U-NoLED</footprint>
      <libsource lib="MX_Alps_Hybrid" part="MX-NoLED" description=""/>
      <sheetpath names="/" tstamps="/"/>
      <tstamp>5F1076AA</tstamp>
    </comp>
    <comp ref="MX36">
      <value>MX-NoLED</value>
      <footprint>MX_Only:MXOnly-1U-NoLED</footprint>
      <libsource lib="MX_Alps_Hybrid" part="MX-NoLED" description=""/>
      <sheetpath names="/" tstamps="/"/>
      <tstamp>5F1076B9</tstamp>
    </comp>
    <comp ref="MX2">
      <value>MX-NoLED</value>
      <footprint>MX_Only:MXOnly-1U-NoLED</footprint>
      <libsource lib="MX_Alps_Hybrid" part="MX-NoLED" description=""/>
      <sheetpath names="/" tstamps="/"/>
      <tstamp>5F1868E7</tstamp>
    </comp>
    <comp ref="MX5">
      <value>MX-NoLED</value>
      <footprint>MX_Only:MXOnly-1U-NoLED</footprint>
      <libsource lib="MX_Alps_Hybrid" part="MX-NoLED" description=""/>
      <sheetpath names="/" tstamps="/"/>
      <tstamp>5F1868F6</tstamp>
    </comp>
    <comp ref="MX8">
      <value>MX-NoLED</value>
      <footprint>MX_Only:MXOnly-1U-NoLED</footprint>
      <libsource lib="MX_Alps_Hybrid" part="MX-NoLED" description=""/>
      <sheetpath names="/" tstamps="/"/>
      <tstamp>5F186905</tstamp>
    </comp>
    <comp ref="MX12">
      <value>MX-NoLED</value>
      <footprint>MX_Only:MXOnly-1U-NoLED</footprint>
      <libsource lib="MX_Alps_Hybrid" part="MX-NoLED" description=""/>
      <sheetpath names="/" tstamps="/"/>
      <tstamp>5F186914</tstamp>
    </comp>
    <comp ref="MX21">
      <value>MX-NoLED</value>
      <footprint>MX_Only:MXOnly-1U-NoLED</footprint>
      <libsource lib="MX_Alps_Hybrid" part="MX-NoLED" description=""/>
      <sheetpath names="/" tstamps="/"/>
      <tstamp>5F186932</tstamp>
    </comp>
    <comp ref="MX24">
      <value>MX-NoLED</value>
      <footprint>MX_Only:MXOnly-1U-NoLED</footprint>
      <libsource lib="MX_Alps_Hybrid" part="MX-NoLED" description=""/>
      <sheetpath names="/" tstamps="/"/>
      <tstamp>5F186941</tstamp>
    </comp>
    <comp ref="MX28">
      <value>MX-NoLED</value>
      <footprint>MX_Only:MXOnly-1U-NoLED</footprint>
      <libsource lib="MX_Alps_Hybrid" part="MX-NoLED" description=""/>
      <sheetpath names="/" tstamps="/"/>
      <tstamp>5F186950</tstamp>
    </comp>
    <comp ref="MX33">
      <value>MX-NoLED</value>
      <footprint>MX_Only:MXOnly-1U-NoLED</footprint>
      <libsource lib="MX_Alps_Hybrid" part="MX-NoLED" description=""/>
      <sheetpath names="/" tstamps="/"/>
      <tstamp>5F18695F</tstamp>
    </comp>
    <comp ref="MX37">
      <value>MX-NoLED</value>
      <footprint>MX_Only:MXOnly-1U-NoLED</footprint>
      <libsource lib="MX_Alps_Hybrid" part="MX-NoLED" description=""/>
      <sheetpath names="/" tstamps="/"/>
      <tstamp>5F18696E</tstamp>
    </comp>
    <comp ref="MX3">
      <value>MX-NoLED</value>
      <footprint>MX_Only:MXOnly-1U-NoLED</footprint>
      <libsource lib="MX_Alps_Hybrid" part="MX-NoLED" description=""/>
      <sheetpath names="/" tstamps="/"/>
      <tstamp>5F1EDB69</tstamp>
    </comp>
    <comp ref="MX6">
      <value>MX-NoLED</value>
      <footprint>MX_Only:MXOnly-1U-NoLED</footprint>
      <libsource lib="MX_Alps_Hybrid" part="MX-NoLED" description=""/>
      <sheetpath names="/" tstamps="/"/>
      <tstamp>5F1EDB78</tstamp>
    </comp>
    <comp ref="MX9">
      <value>MX-NoLED</value>
      <footprint>MX_Only:MXOnly-1U-NoLED</footprint>
      <libsource lib="MX_Alps_Hybrid" part="MX-NoLED" description=""/>
      <sheetpath names="/" tstamps="/"/>
      <tstamp>5F1EDB87</tstamp>
    </comp>
    <comp ref="MX13">
      <value>MX-NoLED</value>
      <footprint>MX_Only:MXOnly-1U-NoLED</footprint>
      <libsource lib="MX_Alps_Hybrid" part="MX-NoLED" description=""/>
      <sheetpath names="/" tstamps="/"/>
      <tstamp>5F1EDB96</tstamp>
    </comp>
    <comp ref="MX18">
      <value>MX-NoLED</value>
      <footprint>MX_Only:MXOnly-1U-NoLED</footprint>
      <libsource lib="MX_Alps_Hybrid" part="MX-NoLED" description=""/>
      <sheetpath names="/" tstamps="/"/>
      <tstamp>5F1EDBA5</tstamp>
    </comp>
    <comp ref="MX22">
      <value>MX-NoLED</value>
      <footprint>MX_Only:MXOnly-1U-NoLED</footprint>
      <libsource lib="MX_Alps_Hybrid" part="MX-NoLED" description=""/>
      <sheetpath names="/" tstamps="/"/>
      <tstamp>5F1EDBB4</tstamp>
    </comp>
    <comp ref="MX25">
      <value>MX-NoLED</value>
      <footprint>MX_Only:MXOnly-1U-NoLED</footprint>
      <libsource lib="MX_Alps_Hybrid" part="MX-NoLED" description=""/>
      <sheetpath names="/" tstamps="/"/>
      <tstamp>5F1EDBC3</tstamp>
    </comp>
    <comp ref="MX29">
      <value>MX-NoLED</value>
      <footprint>MX_Only:MXOnly-1U-NoLED</footprint>
      <libsource lib="MX_Alps_Hybrid" part="MX-NoLED" description=""/>
      <sheetpath names="/" tstamps="/"/>
      <tstamp>5F1EDBD2</tstamp>
    </comp>
    <comp ref="MX34">
      <value>MX-NoLED</value>
      <footprint>MX_Only:MXOnly-1U-NoLED</footprint>
      <libsource lib="MX_Alps_Hybrid" part="MX-NoLED" description=""/>
      <sheetpath names="/" tstamps="/"/>
      <tstamp>5F1EDBE1</tstamp>
    </comp>
    <comp ref="MX38">
      <value>MX-NoLED</value>
      <footprint>MX_Only:MXOnly-1U-NoLED</footprint>
      <libsource lib="MX_Alps_Hybrid" part="MX-NoLED" description=""/>
      <sheetpath names="/" tstamps="/"/>
      <tstamp>5F1EDBF0</tstamp>
    </comp>
    <comp ref="MX19">
      <value>MX-NoLED</value>
      <footprint>MX_Only:MXOnly-1U-NoLED</footprint>
      <libsource lib="MX_Alps_Hybrid" part="MX-NoLED" description=""/>
      <sheetpath names="/" tstamps="/"/>
      <tstamp>5F2028C8</tstamp>
    </comp>
    <comp ref="MX15">
      <value>MX-NoLED</value>
      <footprint>MX_Only:MXOnly-1U-NoLED</footprint>
      <libsource lib="MX_Alps_Hybrid" part="MX-NoLED" description=""/>
      <sheetpath names="/" tstamps="/"/>
      <tstamp>5F2028B9</tstamp>
    </comp>
    <comp ref="MX10">
      <value>MX-NoLED</value>
      <footprint>MX_Only:MXOnly-1U-NoLED</footprint>
      <libsource lib="MX_Alps_Hybrid" part="MX-NoLED" description=""/>
      <sheetpath names="/" tstamps="/"/>
      <tstamp>5F20289B</tstamp>
    </comp>
    <comp ref="SW1">
      <value>SW_Push</value>
      <footprint>Keebio-Parts:SW_SPST_TL3342</footprint>
      <datasheet>~</datasheet>
      <libsource lib="Switch" part="SW_Push" description="Push button switch, generic, two pins"/>
      <sheetpath names="/" tstamps="/"/>
      <tstamp>5F5437F8</tstamp>
    </comp>
    <comp ref="Y1">
      <value>16MHz</value>
      <footprint>Crystal:Resonator_SMD_Murata_CSTxExxV-3Pin_3.0x1.1mm_HandSoldering</footprint>
      <datasheet>~</datasheet>
      <libsource lib="Device" part="Resonator_Small" description="Three pin ceramic resonator, small symbol"/>
      <sheetpath names="/" tstamps="/"/>
      <tstamp>5F5A61F7</tstamp>
    </comp>
    <comp ref="R4">
      <value>10k</value>
      <footprint>Resistor_SMD:R_0603_1608Metric_Pad0.98x0.95mm_HandSolder</footprint>
      <datasheet>~</datasheet>
      <libsource lib="Device" part="R_Small" description="Resistor, small symbol"/>
      <sheetpath names="/" tstamps="/"/>
      <tstamp>5F5D69C4</tstamp>
    </comp>
    <comp ref="R5">
      <value>10k</value>
      <footprint>Resistor_SMD:R_0603_1608Metric_Pad0.98x0.95mm_HandSolder</footprint>
      <datasheet>~</datasheet>
      <libsource lib="Device" part="R_Small" description="Resistor, small symbol"/>
      <sheetpath names="/" tstamps="/"/>
      <tstamp>5F5F289D</tstamp>
    </comp>
    <comp ref="R2">
      <value>22</value>
      <footprint>Resistor_SMD:R_0603_1608Metric_Pad0.98x0.95mm_HandSolder</footprint>
      <datasheet>~</datasheet>
      <libsource lib="Device" part="R_Small" description="Resistor, small symbol"/>
      <sheetpath names="/" tstamps="/"/>
      <tstamp>5F620E03</tstamp>
    </comp>
    <comp ref="R3">
      <value>22</value>
      <footprint>Resistor_SMD:R_0603_1608Metric_Pad0.98x0.95mm_HandSolder</footprint>
      <datasheet>~</datasheet>
      <libsource lib="Device" part="R_Small" description="Resistor, small symbol"/>
      <sheetpath names="/" tstamps="/"/>
      <tstamp>5F6224E2</tstamp>
    </comp>
    <comp ref="C6">
      <value>1uF</value>
      <footprint>Capacitor_SMD:C_0603_1608Metric_Pad1.08x0.95mm_HandSolder</footprint>
      <datasheet>~</datasheet>
      <libsource lib="Device" part="C_Small" description="Unpolarized capacitor, small symbol"/>
      <sheetpath names="/" tstamps="/"/>
      <tstamp>5F691F21</tstamp>
    </comp>
    <comp ref="C1">
      <value>.1uF</value>
      <footprint>Capacitor_SMD:C_0603_1608Metric_Pad1.08x0.95mm_HandSolder</footprint>
      <datasheet>~</datasheet>
      <libsource lib="Device" part="C_Small" description="Unpolarized capacitor, small symbol"/>
      <sheetpath names="/" tstamps="/"/>
      <tstamp>5F6C5A88</tstamp>
    </comp>
    <comp ref="C2">
      <value>.1uF</value>
      <footprint>Capacitor_SMD:C_0603_1608Metric_Pad1.08x0.95mm_HandSolder</footprint>
      <datasheet>~</datasheet>
      <libsource lib="Device" part="C_Small" description="Unpolarized capacitor, small symbol"/>
      <sheetpath names="/" tstamps="/"/>
      <tstamp>5F6C6E92</tstamp>
    </comp>
    <comp ref="C4">
      <value>.1uF</value>
      <footprint>Capacitor_SMD:C_0603_1608Metric_Pad1.08x0.95mm_HandSolder</footprint>
      <datasheet>~</datasheet>
      <libsource lib="Device" part="C_Small" description="Unpolarized capacitor, small symbol"/>
      <sheetpath names="/" tstamps="/"/>
      <tstamp>5F6C7CF3</tstamp>
    </comp>
    <comp ref="C5">
      <value>10uF</value>
      <footprint>Capacitor_SMD:C_0603_1608Metric_Pad1.08x0.95mm_HandSolder</footprint>
      <datasheet>~</datasheet>
      <libsource lib="Device" part="C_Small" description="Unpolarized capacitor, small symbol"/>
      <sheetpath names="/" tstamps="/"/>
      <tstamp>5F6C8E6F</tstamp>
    </comp>
    <comp ref="MX4">
      <value>MX-NoLED</value>
      <footprint>MX_Only:MXOnly-1U-NoLED</footprint>
      <libsource lib="MX_Alps_Hybrid" part="MX-NoLED" description=""/>
      <sheetpath names="/" tstamps="/"/>
      <tstamp>5F0F2012</tstamp>
    </comp>
    <comp ref="MX35">
      <value>MX-NoLED</value>
      <footprint>MX_Only:MXOnly-1U-NoLED</footprint>
      <libsource lib="MX_Alps_Hybrid" part="MX-NoLED" description=""/>
      <sheetpath names="/" tstamps="/"/>
      <tstamp>5F202904</tstamp>
    </comp>
    <comp ref="MX30">
      <value>MX-NoLED</value>
      <footprint>MX_Only:MXOnly-1U-NoLED</footprint>
      <libsource lib="MX_Alps_Hybrid" part="MX-NoLED" description=""/>
      <sheetpath names="/" tstamps="/"/>
      <tstamp>5F2028E6</tstamp>
    </comp>
    <comp ref="MX26">
      <value>MX-NoLED</value>
      <footprint>MX_Only:MXOnly-1U-NoLED</footprint>
      <libsource lib="MX_Alps_Hybrid" part="MX-NoLED" description=""/>
      <sheetpath names="/" tstamps="/"/>
      <tstamp>5F2028D7</tstamp>
    </comp>
    <comp ref="C101">
      <value>.1uF</value>
      <footprint>Capacitor_SMD:C_0603_1608Metric_Pad1.08x0.95mm_HandSolder</footprint>
      <datasheet>~</datasheet>
      <libsource lib="Device" part="C_Small" description="Unpolarized capacitor, small symbol"/>
      <sheetpath names="/" tstamps="/"/>
      <tstamp>5FA3FBE2</tstamp>
    </comp>
    <comp ref="MX17">
      <value>MX-NoLED</value>
      <footprint>MX_Only:MXOnly-1U-NoLED</footprint>
      <libsource lib="MX_Alps_Hybrid" part="MX-NoLED" description=""/>
      <sheetpath names="/" tstamps="/"/>
      <tstamp>5F186923</tstamp>
    </comp>
    <comp ref="D105">
      <value>BAV70</value>
      <footprint>Package_TO_SOT_SMD:SOT-23</footprint>
      <datasheet>https://assets.nexperia.com/documents/data-sheet/BAV70_SER.pdf</datasheet>
      <libsource lib="Diode" part="BAV70" description="Dual 100V 215mA high-speed switching diodes, common cathode, SOT-23"/>
      <sheetpath names="/" tstamps="/"/>
      <tstamp>61529FF5</tstamp>
    </comp>
    <comp ref="D110">
      <value>BAV70</value>
      <footprint>Package_TO_SOT_SMD:SOT-23</footprint>
      <datasheet>https://assets.nexperia.com/documents/data-sheet/BAV70_SER.pdf</datasheet>
      <libsource lib="Diode" part="BAV70" description="Dual 100V 215mA high-speed switching diodes, common cathode, SOT-23"/>
      <sheetpath names="/" tstamps="/"/>
      <tstamp>61536A76</tstamp>
    </comp>
    <comp ref="D114">
      <value>BAV70</value>
      <footprint>Package_TO_SOT_SMD:SOT-23</footprint>
      <datasheet>https://assets.nexperia.com/documents/data-sheet/BAV70_SER.pdf</datasheet>
      <libsource lib="Diode" part="BAV70" description="Dual 100V 215mA high-speed switching diodes, common cathode, SOT-23"/>
      <sheetpath names="/" tstamps="/"/>
      <tstamp>615414B2</tstamp>
    </comp>
    <comp ref="D117">
      <value>BAV70</value>
      <footprint>Package_TO_SOT_SMD:SOT-23</footprint>
      <datasheet>https://assets.nexperia.com/documents/data-sheet/BAV70_SER.pdf</datasheet>
      <libsource lib="Diode" part="BAV70" description="Dual 100V 215mA high-speed switching diodes, common cathode, SOT-23"/>
      <sheetpath names="/" tstamps="/"/>
      <tstamp>6154BCCD</tstamp>
    </comp>
    <comp ref="D113">
      <value>BAV70</value>
      <footprint>Package_TO_SOT_SMD:SOT-23</footprint>
      <datasheet>https://assets.nexperia.com/documents/data-sheet/BAV70_SER.pdf</datasheet>
      <libsource lib="Diode" part="BAV70" description="Dual 100V 215mA high-speed switching diodes, common cathode, SOT-23"/>
      <sheetpath names="/" tstamps="/"/>
      <tstamp>61556B05</tstamp>
    </comp>
    <comp ref="D116">
      <value>BAV70</value>
      <footprint>Package_TO_SOT_SMD:SOT-23</footprint>
      <datasheet>https://assets.nexperia.com/documents/data-sheet/BAV70_SER.pdf</datasheet>
      <libsource lib="Diode" part="BAV70" description="Dual 100V 215mA high-speed switching diodes, common cathode, SOT-23"/>
      <sheetpath names="/" tstamps="/"/>
      <tstamp>6156131C</tstamp>
    </comp>
    <comp ref="D104">
      <value>BAV70</value>
      <footprint>Package_TO_SOT_SMD:SOT-23</footprint>
      <datasheet>https://assets.nexperia.com/documents/data-sheet/BAV70_SER.pdf</datasheet>
      <libsource lib="Diode" part="BAV70" description="Dual 100V 215mA high-speed switching diodes, common cathode, SOT-23"/>
      <sheetpath names="/" tstamps="/"/>
      <tstamp>6156C35D</tstamp>
    </comp>
    <comp ref="D109">
      <value>BAV70</value>
      <footprint>Package_TO_SOT_SMD:SOT-23</footprint>
      <datasheet>https://assets.nexperia.com/documents/data-sheet/BAV70_SER.pdf</datasheet>
      <libsource lib="Diode" part="BAV70" description="Dual 100V 215mA high-speed switching diodes, common cathode, SOT-23"/>
      <sheetpath names="/" tstamps="/"/>
      <tstamp>61576CC8</tstamp>
    </comp>
    <comp ref="D108">
      <value>BAV70</value>
      <footprint>Package_TO_SOT_SMD:SOT-23</footprint>
      <datasheet>https://assets.nexperia.com/documents/data-sheet/BAV70_SER.pdf</datasheet>
      <libsource lib="Diode" part="BAV70" description="Dual 100V 215mA high-speed switching diodes, common cathode, SOT-23"/>
      <sheetpath names="/" tstamps="/"/>
      <tstamp>61581732</tstamp>
    </comp>
    <comp ref="D103">
      <value>BAV70</value>
      <footprint>Package_TO_SOT_SMD:SOT-23</footprint>
      <datasheet>https://assets.nexperia.com/documents/data-sheet/BAV70_SER.pdf</datasheet>
      <libsource lib="Diode" part="BAV70" description="Dual 100V 215mA high-speed switching diodes, common cathode, SOT-23"/>
      <sheetpath names="/" tstamps="/"/>
      <tstamp>6158C034</tstamp>
    </comp>
    <comp ref="D107">
      <value>BAV70</value>
      <footprint>Package_TO_SOT_SMD:SOT-23</footprint>
      <datasheet>https://assets.nexperia.com/documents/data-sheet/BAV70_SER.pdf</datasheet>
      <libsource lib="Diode" part="BAV70" description="Dual 100V 215mA high-speed switching diodes, common cathode, SOT-23"/>
      <sheetpath names="/" tstamps="/"/>
      <tstamp>615969D1</tstamp>
    </comp>
    <comp ref="D102">
      <value>BAV70</value>
      <footprint>Package_TO_SOT_SMD:SOT-23</footprint>
      <datasheet>https://assets.nexperia.com/documents/data-sheet/BAV70_SER.pdf</datasheet>
      <libsource lib="Diode" part="BAV70" description="Dual 100V 215mA high-speed switching diodes, common cathode, SOT-23"/>
      <sheetpath names="/" tstamps="/"/>
      <tstamp>615A127E</tstamp>
    </comp>
    <comp ref="D101">
      <value>BAV70</value>
      <footprint>Package_TO_SOT_SMD:SOT-23</footprint>
      <datasheet>https://assets.nexperia.com/documents/data-sheet/BAV70_SER.pdf</datasheet>
      <libsource lib="Diode" part="BAV70" description="Dual 100V 215mA high-speed switching diodes, common cathode, SOT-23"/>
      <sheetpath names="/" tstamps="/"/>
      <tstamp>615ABB99</tstamp>
    </comp>
    <comp ref="D106">
      <value>BAV70</value>
      <footprint>Package_TO_SOT_SMD:SOT-23</footprint>
      <datasheet>https://assets.nexperia.com/documents/data-sheet/BAV70_SER.pdf</datasheet>
      <libsource lib="Diode" part="BAV70" description="Dual 100V 215mA high-speed switching diodes, common cathode, SOT-23"/>
      <sheetpath names="/" tstamps="/"/>
      <tstamp>615B634C</tstamp>
    </comp>
    <comp ref="D111">
      <value>BAV70</value>
      <footprint>Package_TO_SOT_SMD:SOT-23</footprint>
      <datasheet>https://assets.nexperia.com/documents/data-sheet/BAV70_SER.pdf</datasheet>
      <libsource lib="Diode" part="BAV70" description="Dual 100V 215mA high-speed switching diodes, common cathode, SOT-23"/>
      <sheetpath names="/" tstamps="/"/>
      <tstamp>615C0A9B</tstamp>
    </comp>
    <comp ref="D115">
      <value>BAV70</value>
      <footprint>Package_TO_SOT_SMD:SOT-23</footprint>
      <datasheet>https://assets.nexperia.com/documents/data-sheet/BAV70_SER.pdf</datasheet>
      <libsource lib="Diode" part="BAV70" description="Dual 100V 215mA high-speed switching diodes, common cathode, SOT-23"/>
      <sheetpath names="/" tstamps="/"/>
      <tstamp>615CB3B1</tstamp>
    </comp>
    <comp ref="D112">
      <value>BAV70</value>
      <footprint>Package_TO_SOT_SMD:SOT-23</footprint>
      <datasheet>https://assets.nexperia.com/documents/data-sheet/BAV70_SER.pdf</datasheet>
      <libsource lib="Diode" part="BAV70" description="Dual 100V 215mA high-speed switching diodes, common cathode, SOT-23"/>
      <sheetpath names="/" tstamps="/"/>
      <tstamp>615D5EFC</tstamp>
    </comp>
    <comp ref="D118">
      <value>BAV70</value>
      <footprint>Package_TO_SOT_SMD:SOT-23</footprint>
      <datasheet>https://assets.nexperia.com/documents/data-sheet/BAV70_SER.pdf</datasheet>
      <libsource lib="Diode" part="BAV70" description="Dual 100V 215mA high-speed switching diodes, common cathode, SOT-23"/>
      <sheetpath names="/" tstamps="/"/>
      <tstamp>6161CF78</tstamp>
    </comp>
    <comp ref="U101">
      <value>ATmega32U4-A</value>
      <footprint>Package_QFP:TQFP-44_10x10mm_P0.8mm</footprint>
      <datasheet>http://ww1.microchip.com/downloads/en/DeviceDoc/Atmel-7766-8-bit-AVR-ATmega16U4-32U4_Datasheet.pdf</datasheet>
      <libsource lib="MCU_Microchip_ATmega" part="ATmega32U4-A" description="16MHz, 32kB Flash, 2.5kB SRAM, 1kB EEPROM, USB 2.0, TQFP-44"/>
      <sheetpath names="/" tstamps="/"/>
      <tstamp>6106D3C2</tstamp>
    </comp>
    <comp ref="U102">
      <value>PRTR5V0U2X</value>
      <footprint>Package_TO_SOT_SMD:SOT-143</footprint>
      <libsource lib="keebio" part="PRTR5V0U2X" description=""/>
      <sheetpath names="/" tstamps="/"/>
      <tstamp>61012558</tstamp>
    </comp>
    <comp ref="R101">
      <value>5.1k</value>
      <footprint>Resistor_SMD:R_0603_1608Metric</footprint>
      <datasheet>~</datasheet>
      <libsource lib="Device" part="R_Small" description="Resistor, small symbol"/>
      <sheetpath names="/" tstamps="/"/>
      <tstamp>6109A343</tstamp>
    </comp>
    <comp ref="R102">
      <value>5.1k</value>
      <footprint>Resistor_SMD:R_0603_1608Metric</footprint>
      <datasheet>~</datasheet>
      <libsource lib="Device" part="R_Small" description="Resistor, small symbol"/>
      <sheetpath names="/" tstamps="/"/>
      <tstamp>6109C8CE</tstamp>
    </comp>
    <comp ref="F101">
      <value>700mA</value>
      <footprint>Fuse:Fuse_0603_1608Metric</footprint>
      <datasheet>~</datasheet>
      <libsource lib="Device" part="Fuse_Small" description="Fuse, small symbol"/>
      <sheetpath names="/" tstamps="/"/>
      <tstamp>6106EA81</tstamp>
    </comp>
    <comp ref="L101">
      <value>600R@100MHz</value>
      <footprint>Inductor_SMD:L_0603_1608Metric</footprint>
      <datasheet>~</datasheet>
      <libsource lib="Device" part="L_Small" description="Inductor, small symbol"/>
      <sheetpath names="/" tstamps="/"/>
      <tstamp>6107A7F4</tstamp>
    </comp>
    <comp ref="USB101">
      <value>HRO-TYPE-C-31-M-12</value>
      <footprint>Type-C:HRO-TYPE-C-31-M-12-Assembly</footprint>
      <libsource lib="keebio" part="HRO-TYPE-C-31-M-12" description=""/>
      <sheetpath names="/" tstamps="/"/>
      <tstamp>6100D0CA</tstamp>
    </comp>
  </components>
  <libparts>
    <libpart lib="Device" part="C_Small">
      <description>Unpolarized capacitor, small symbol</description>
      <docs>~</docs>
      <footprints>
        <fp>C_*</fp>
      </footprints>
      <fields>
        <field name="Reference">C</field>
        <field name="Value">C_Small</field>
      </fields>
      <pins>
        <pin num="1" name="~" type="passive"/>
        <pin num="2" name="~" type="passive"/>
      </pins>
    </libpart>
    <libpart lib="Device" part="Fuse_Small">
      <description>Fuse, small symbol</description>
      <docs>~</docs>
      <footprints>
        <fp>SM*</fp>
      </footprints>
      <fields>
        <field name="Reference">F</field>
        <field name="Value">Fuse_Small</field>
      </fields>
      <pins>
        <pin num="1" name="~" type="passive"/>
        <pin num="2" name="~" type="passive"/>
      </pins>
    </libpart>
    <libpart lib="Device" part="L_Small">
      <description>Inductor, small symbol</description>
      <docs>~</docs>
      <footprints>
        <fp>Choke_*</fp>
        <fp>*Coil*</fp>
        <fp>Inductor_*</fp>
        <fp>L_*</fp>
      </footprints>
      <fields>
        <field name="Reference">L</field>
        <field name="Value">L_Small</field>
      </fields>
      <pins>
        <pin num="1" name="~" type="passive"/>
        <pin num="2" name="~" type="passive"/>
      </pins>
    </libpart>
    <libpart lib="Device" part="R_Small">
      <description>Resistor, small symbol</description>
      <docs>~</docs>
      <footprints>
        <fp>R_*</fp>
      </footprints>
      <fields>
        <field name="Reference">R</field>
        <field name="Value">R_Small</field>
      </fields>
      <pins>
        <pin num="1" name="~" type="passive"/>
        <pin num="2" name="~" type="passive"/>
      </pins>
    </libpart>
    <libpart lib="Device" part="Resonator_Small">
      <description>Three pin ceramic resonator, small symbol</description>
      <docs>~</docs>
      <footprints>
        <fp>Filter*</fp>
        <fp>Resonator*</fp>
      </footprints>
      <fields>
        <field name="Reference">Y</field>
        <field name="Value">Resonator_Small</field>
      </fields>
      <pins>
        <pin num="1" name="1" type="passive"/>
        <pin num="2" name="2" type="passive"/>
        <pin num="3" name="3" type="passive"/>
      </pins>
    </libpart>
    <libpart lib="Diode" part="BAV70">
      <description>Dual 100V 215mA high-speed switching diodes, common cathode, SOT-23</description>
      <docs>https://assets.nexperia.com/documents/data-sheet/BAV70_SER.pdf</docs>
      <footprints>
        <fp>SOT?23*</fp>
      </footprints>
      <fields>
        <field name="Reference">D</field>
        <field name="Value">BAV70</field>
        <field name="Footprint">Package_TO_SOT_SMD:SOT-23</field>
      </fields>
      <pins>
        <pin num="1" name="A" type="passive"/>
        <pin num="2" name="A" type="passive"/>
        <pin num="3" name="K" type="passive"/>
      </pins>
    </libpart>
    <libpart lib="MCU_Microchip_ATmega" part="ATmega16U4-A">
      <aliases>
        <alias>ATmega16U4RC-A</alias>
        <alias>ATmega32U4-A</alias>
        <alias>ATmega32U4RC-A</alias>
      </aliases>
      <description>16MHz, 16kB Flash, 1.25kB SRAM, 512B EEPROM, USB 2.0, TQFP-44</description>
      <docs>http://ww1.microchip.com/downloads/en/DeviceDoc/Atmel-7766-8-bit-AVR-ATmega16U4-32U4_Datasheet.pdf</docs>
      <footprints>
        <fp>TQFP*10x10mm*P0.8mm*</fp>
      </footprints>
      <fields>
        <field name="Reference">U</field>
        <field name="Value">ATmega16U4-A</field>
        <field name="Footprint">Package_QFP:TQFP-44_10x10mm_P0.8mm</field>
      </fields>
      <pins>
        <pin num="1" name="PE6" type="BiDi"/>
        <pin num="2" name="UVCC" type="power_in"/>
        <pin num="3" name="D-" type="BiDi"/>
        <pin num="4" name="D+" type="BiDi"/>
        <pin num="5" name="UGND" type="passive"/>
        <pin num="6" name="UCAP" type="passive"/>
        <pin num="7" name="VBUS" type="input"/>
        <pin num="8" name="PB0" type="BiDi"/>
        <pin num="9" name="PB1" type="BiDi"/>
        <pin num="10" name="PB2" type="BiDi"/>
        <pin num="11" name="PB3" type="BiDi"/>
        <pin num="12" name="PB7" type="BiDi"/>
        <pin num="13" name="~RESET" type="input"/>
        <pin num="14" name="VCC" type="power_in"/>
        <pin num="15" name="GND" type="power_in"/>
        <pin num="16" name="XTAL2" type="output"/>
        <pin num="17" name="XTAL1" type="input"/>
        <pin num="18" name="PD0" type="BiDi"/>
        <pin num="19" name="PD1" type="BiDi"/>
        <pin num="20" name="PD2" type="BiDi"/>
        <pin num="21" name="PD3" type="BiDi"/>
        <pin num="22" name="PD5" type="BiDi"/>
        <pin num="23" name="GND" type="passive"/>
        <pin num="24" name="AVCC" type="power_in"/>
        <pin num="25" name="PD4" type="BiDi"/>
        <pin num="26" name="PD6" type="BiDi"/>
        <pin num="27" name="PD7" type="BiDi"/>
        <pin num="28" name="PB4" type="BiDi"/>
        <pin num="29" name="PB5" type="BiDi"/>
        <pin num="30" name="PB6" type="BiDi"/>
        <pin num="31" name="PC6" type="BiDi"/>
        <pin num="32" name="PC7" type="BiDi"/>
        <pin num="33" name="~HWB~/PE2" type="BiDi"/>
        <pin num="34" name="VCC" type="passive"/>
        <pin num="35" name="GND" type="passive"/>
        <pin num="36" name="PF7" type="BiDi"/>
        <pin num="37" name="PF6" type="BiDi"/>
        <pin num="38" name="PF5" type="BiDi"/>
        <pin num="39" name="PF4" type="BiDi"/>
        <pin num="40" name="PF1" type="BiDi"/>
        <pin num="41" name="PF0" type="BiDi"/>
        <pin num="42" name="AREF" type="passive"/>
        <pin num="43" name="GND" type="passive"/>
        <pin num="44" name="AVCC" type="passive"/>
      </pins>
    </libpart>
    <libpart lib="MX_Alps_Hybrid" part="MX-NoLED">
      <fields>
        <field name="Reference">MX</field>
        <field name="Value">MX-NoLED</field>
      </fields>
      <pins>
        <pin num="1" name="COL" type="passive"/>
        <pin num="2" name="ROW" type="passive"/>
      </pins>
    </libpart>
    <libpart lib="Switch" part="SW_Push">
      <description>Push button switch, generic, two pins</description>
      <docs>~</docs>
      <fields>
        <field name="Reference">SW</field>
        <field name="Value">SW_Push</field>
      </fields>
      <pins>
        <pin num="1" name="1" type="passive"/>
        <pin num="2" name="2" type="passive"/>
      </pins>
    </libpart>
    <libpart lib="keebio" part="HRO-TYPE-C-31-M-12">
      <fields>
        <field name="Reference">USB</field>
        <field name="Value">HRO-TYPE-C-31-M-12</field>
      </fields>
      <pins>
        <pin num="1" name="GND" type="input"/>
        <pin num="2" name="VBUS" type="input"/>
        <pin num="3" name="SBU2" type="input"/>
        <pin num="4" name="CC1" type="input"/>
        <pin num="5" name="DN2" type="input"/>
        <pin num="6" name="DP1" type="input"/>
        <pin num="7" name="DN1" type="input"/>
        <pin num="8" name="DP2" type="input"/>
        <pin num="9" name="SBU1" type="input"/>
        <pin num="10" name="CC2" type="input"/>
        <pin num="11" name="VBUS" type="input"/>
        <pin num="12" name="GND" type="input"/>
        <pin num="13" name="SHIELD" type="input"/>
      </pins>
    </libpart>
    <libpart lib="keebio" part="PRTR5V0U2X">
      <fields>
        <field name="Reference">U</field>
        <field name="Value">PRTR5V0U2X</field>
      </fields>
      <pins>
        <pin num="1" name="GND" type="input"/>
        <pin num="2" name="I/O1" type="input"/>
        <pin num="3" name="I/O2" type="input"/>
        <pin num="4" name="VCC" type="input"/>
      </pins>
    </libpart>
  </libparts>
  <libraries>
    <library logical="Device">
      <uri>/Users/tjcampie/Documents/Keyboards/KiCad Libraries/kicad-symbols/Device.lib</uri>
    </library>
    <library logical="Diode">
      <uri>/Users/tjcampie/Documents/Keyboards/KiCad Libraries/kicad-symbols/Diode.lib</uri>
    </library>
    <library logical="MCU_Microchip_ATmega">
      <uri>/Users/tjcampie/Documents/Keyboards/KiCad Libraries/kicad-symbols/MCU_Microchip_ATmega.lib</uri>
    </library>
    <library logical="MX_Alps_Hybrid">
      <uri>/Users/tjcampie/Documents/Keyboards/KiCad Libraries/MX_Alps_Hybrid/Schematic Library/MX_Alps_Hybrid.lib</uri>
    </library>
    <library logical="Switch">
      <uri>/Users/tjcampie/Documents/Keyboards/KiCad Libraries/kicad-symbols/Switch.lib</uri>
    </library>
    <library logical="keebio">
      <uri>/Users/tjcampie/Documents/Keyboards/KiCad Libraries/keebio-components/keebio.lib</uri>
    </library>
  </libraries>
  <nets>
    <net code="1" name="Net-(D101-Pad1)">
      <node ref="MX1" pin="2"/>
      <node ref="D101" pin="1"/>
    </net>
    <net code="2" name="Net-(D102-Pad1)">
      <node ref="MX7" pin="2"/>
      <node ref="D102" pin="1"/>
    </net>
    <net code="3" name="Net-(D102-Pad2)">
      <node ref="MX11" pin="2"/>
      <node ref="D102" pin="2"/>
    </net>
    <net code="4" name="Net-(D103-Pad1)">
      <node ref="MX16" pin="2"/>
      <node ref="D103" pin="1"/>
    </net>
    <net code="5" name="Net-(D103-Pad2)">
      <node ref="MX20" pin="2"/>
      <node ref="D103" pin="2"/>
    </net>
    <net code="6" name="Net-(D104-Pad1)">
      <node ref="D104" pin="1"/>
      <node ref="MX23" pin="2"/>
    </net>
    <net code="7" name="Net-(D104-Pad2)">
      <node ref="D104" pin="2"/>
      <node ref="MX27" pin="2"/>
    </net>
    <net code="8" name="Net-(D105-Pad1)">
      <node ref="D105" pin="1"/>
      <node ref="MX32" pin="2"/>
    </net>
    <net code="9" name="Net-(D105-Pad2)">
      <node ref="MX36" pin="2"/>
      <node ref="D105" pin="2"/>
    </net>
    <net code="10" name="Net-(D106-Pad1)">
      <node ref="D106" pin="1"/>
      <node ref="MX2" pin="2"/>
    </net>
    <net code="11" name="Net-(D106-Pad2)">
      <node ref="D106" pin="2"/>
      <node ref="MX5" pin="2"/>
    </net>
    <net code="12" name="Net-(D107-Pad1)">
      <node ref="MX8" pin="2"/>
      <node ref="D107" pin="1"/>
    </net>
    <net code="13" name="Net-(D107-Pad2)">
      <node ref="MX12" pin="2"/>
      <node ref="D107" pin="2"/>
    </net>
    <net code="14" name="Net-(D108-Pad2)">
      <node ref="D108" pin="2"/>
      <node ref="MX21" pin="2"/>
    </net>
    <net code="15" name="Net-(D109-Pad1)">
      <node ref="MX24" pin="2"/>
      <node ref="D109" pin="1"/>
    </net>
    <net code="16" name="Net-(D109-Pad2)">
      <node ref="MX28" pin="2"/>
      <node ref="D109" pin="2"/>
    </net>
    <net code="17" name="Net-(D110-Pad1)">
      <node ref="MX33" pin="2"/>
      <node ref="D110" pin="1"/>
    </net>
    <net code="18" name="Net-(D110-Pad2)">
      <node ref="MX37" pin="2"/>
      <node ref="D110" pin="2"/>
    </net>
    <net code="19" name="Net-(D111-Pad1)">
      <node ref="D111" pin="1"/>
      <node ref="MX3" pin="2"/>
    </net>
    <net code="20" name="Col1">
      <node ref="MX15" pin="1"/>
      <node ref="MX4" pin="1"/>
      <node ref="MX5" pin="1"/>
      <node ref="MX6" pin="1"/>
      <node ref="U101" pin="28"/>
    </net>
    <net code="21" name="Net-(D111-Pad2)">
      <node ref="D111" pin="2"/>
      <node ref="MX6" pin="2"/>
    </net>
    <net code="22" name="Col2">
      <node ref="U101" pin="29"/>
      <node ref="MX8" pin="1"/>
      <node ref="MX7" pin="1"/>
      <node ref="MX9" pin="1"/>
    </net>
    <net code="23" name="Net-(D112-Pad1)">
      <node ref="D112" pin="1"/>
      <node ref="MX9" pin="2"/>
    </net>
    <net code="24" name="Net-(D112-Pad2)">
      <node ref="MX13" pin="2"/>
      <node ref="D112" pin="2"/>
    </net>
    <net code="25" name="Net-(D118-Pad1)">
      <node ref="MX18" pin="2"/>
      <node ref="D118" pin="1"/>
    </net>
    <net code="26" name="Col5">
      <node ref="MX22" pin="1"/>
      <node ref="MX20" pin="1"/>
      <node ref="MX21" pin="1"/>
      <node ref="U101" pin="36"/>
    </net>
    <net code="27" name="Net-(D118-Pad2)">
      <node ref="MX22" pin="2"/>
      <node ref="D118" pin="2"/>
    </net>
    <net code="28" name="Net-(D113-Pad1)">
      <node ref="MX25" pin="2"/>
      <node ref="D113" pin="1"/>
    </net>
    <net code="29" name="Net-(D113-Pad2)">
      <node ref="MX29" pin="2"/>
      <node ref="D113" pin="2"/>
    </net>
    <net code="30" name="Col8">
      <node ref="MX32" pin="1"/>
      <node ref="MX34" pin="1"/>
      <node ref="U101" pin="39"/>
      <node ref="MX33" pin="1"/>
    </net>
    <net code="31" name="Net-(D114-Pad1)">
      <node ref="D114" pin="1"/>
      <node ref="MX34" pin="2"/>
    </net>
    <net code="32" name="Net-(D114-Pad2)">
      <node ref="MX38" pin="2"/>
      <node ref="D114" pin="2"/>
    </net>
    <net code="33" name="Col3">
      <node ref="MX12" pin="1"/>
      <node ref="MX13" pin="1"/>
      <node ref="U101" pin="30"/>
      <node ref="MX11" pin="1"/>
      <node ref="MX19" pin="1"/>
    </net>
    <net code="34" name="Net-(D116-Pad1)">
      <node ref="D116" pin="1"/>
      <node ref="MX19" pin="2"/>
    </net>
    <net code="35" name="Net-(D115-Pad2)">
      <node ref="D115" pin="2"/>
      <node ref="MX15" pin="2"/>
    </net>
    <net code="36" name="Col0">
      <node ref="MX1" pin="1"/>
      <node ref="MX10" pin="1"/>
      <node ref="MX3" pin="1"/>
      <node ref="MX2" pin="1"/>
      <node ref="U101" pin="27"/>
    </net>
    <net code="37" name="Net-(D115-Pad1)">
      <node ref="D115" pin="1"/>
      <node ref="MX10" pin="2"/>
    </net>
    <net code="38" name="Net-(U101-Pad17)">
      <node ref="U101" pin="17"/>
      <node ref="Y1" pin="1"/>
    </net>
    <net code="39" name="Net-(U101-Pad16)">
      <node ref="U101" pin="16"/>
      <node ref="Y1" pin="3"/>
    </net>
    <net code="40" name="GND">
      <node ref="C5" pin="2"/>
      <node ref="C4" pin="2"/>
      <node ref="C2" pin="2"/>
      <node ref="C1" pin="2"/>
      <node ref="C6" pin="2"/>
      <node ref="U101" pin="15"/>
      <node ref="R5" pin="2"/>
      <node ref="U101" pin="23"/>
      <node ref="Y1" pin="2"/>
      <node ref="SW1" pin="1"/>
      <node ref="U101" pin="35"/>
      <node ref="U101" pin="43"/>
      <node ref="U101" pin="5"/>
      <node ref="U102" pin="1"/>
      <node ref="C101" pin="2"/>
      <node ref="L101" pin="1"/>
      <node ref="R101" pin="1"/>
      <node ref="R102" pin="2"/>
    </net>
    <net code="41" name="Net-(R4-Pad2)">
      <node ref="SW1" pin="2"/>
      <node ref="R4" pin="2"/>
      <node ref="U101" pin="13"/>
    </net>
    <net code="42" name="+5V">
      <node ref="C101" pin="1"/>
      <node ref="F101" pin="2"/>
      <node ref="U102" pin="4"/>
      <node ref="U101" pin="7"/>
      <node ref="U101" pin="44"/>
      <node ref="U101" pin="34"/>
      <node ref="R4" pin="1"/>
      <node ref="U101" pin="24"/>
      <node ref="U101" pin="2"/>
      <node ref="U101" pin="14"/>
      <node ref="C1" pin="1"/>
      <node ref="C2" pin="1"/>
      <node ref="C4" pin="1"/>
      <node ref="C5" pin="1"/>
    </net>
    <net code="43" name="Net-(R5-Pad1)">
      <node ref="R5" pin="1"/>
      <node ref="U101" pin="33"/>
    </net>
    <net code="44" name="Net-(R2-Pad1)">
      <node ref="R2" pin="1"/>
      <node ref="U101" pin="4"/>
    </net>
    <net code="45" name="D+">
      <node ref="R2" pin="2"/>
      <node ref="U102" pin="3"/>
      <node ref="USB101" pin="8"/>
      <node ref="USB101" pin="6"/>
    </net>
    <net code="46" name="Net-(R3-Pad1)">
      <node ref="R3" pin="1"/>
      <node ref="U101" pin="3"/>
    </net>
    <net code="47" name="D-">
      <node ref="USB101" pin="7"/>
      <node ref="R3" pin="2"/>
      <node ref="USB101" pin="5"/>
      <node ref="U102" pin="2"/>
    </net>
    <net code="48" name="Net-(C6-Pad1)">
      <node ref="C6" pin="1"/>
      <node ref="U101" pin="6"/>
    </net>
    <net code="50" name="Net-(D101-Pad2)">
      <node ref="MX4" pin="2"/>
      <node ref="D101" pin="2"/>
    </net>
    <net code="51" name="Col7">
      <node ref="MX28" pin="1"/>
      <node ref="U101" pin="38"/>
      <node ref="MX27" pin="1"/>
      <node ref="MX30" pin="1"/>
      <node ref="MX29" pin="1"/>
    </net>
    <net code="52" name="Col9">
      <node ref="MX35" pin="1"/>
      <node ref="U101" pin="40"/>
      <node ref="MX36" pin="1"/>
      <node ref="MX37" pin="1"/>
      <node ref="MX38" pin="1"/>
    </net>
    <net code="53" name="Net-(D117-Pad2)">
      <node ref="MX35" pin="2"/>
      <node ref="D117" pin="2"/>
    </net>
    <net code="54" name="Net-(D117-Pad1)">
      <node ref="MX30" pin="2"/>
      <node ref="D117" pin="1"/>
    </net>
    <net code="55" name="Col6">
      <node ref="MX23" pin="1"/>
      <node ref="U101" pin="37"/>
      <node ref="MX25" pin="1"/>
      <node ref="MX24" pin="1"/>
      <node ref="MX26" pin="1"/>
    </net>
    <net code="56" name="Net-(D116-Pad2)">
      <node ref="D116" pin="2"/>
      <node ref="MX26" pin="2"/>
    </net>
    <net code="57" name="Net-(U101-Pad1)">
      <node ref="U101" pin="1"/>
    </net>
    <net code="59" name="Col4">
      <node ref="MX18" pin="1"/>
      <node ref="MX16" pin="1"/>
      <node ref="MX17" pin="1"/>
      <node ref="U101" pin="31"/>
    </net>
    <net code="60" name="Net-(D108-Pad1)">
      <node ref="D108" pin="1"/>
      <node ref="MX17" pin="2"/>
    </net>
    <net code="61" name="Net-(U101-Pad22)">
      <node ref="U101" pin="22"/>
    </net>
    <net code="62" name="Net-(U101-Pad10)">
      <node ref="U101" pin="10"/>
    </net>
    <net code="63" name="ROW3">
      <node ref="U101" pin="11"/>
      <node ref="D115" pin="3"/>
      <node ref="D116" pin="3"/>
      <node ref="D117" pin="3"/>
    </net>
    <net code="64" name="ROW2">
      <node ref="D113" pin="3"/>
      <node ref="D112" pin="3"/>
      <node ref="U101" pin="12"/>
      <node ref="D111" pin="3"/>
      <node ref="D118" pin="3"/>
      <node ref="D114" pin="3"/>
    </net>
    <net code="65" name="Net-(U101-Pad18)">
      <node ref="U101" pin="18"/>
    </net>
    <net code="66" name="Net-(U101-Pad19)">
      <node ref="U101" pin="19"/>
    </net>
    <net code="67" name="Net-(U101-Pad20)">
      <node ref="U101" pin="20"/>
    </net>
    <net code="68" name="Net-(U101-Pad21)">
      <node ref="U101" pin="21"/>
    </net>
    <net code="69" name="Net-(U101-Pad25)">
      <node ref="U101" pin="25"/>
    </net>
    <net code="70" name="ROW1">
      <node ref="D108" pin="3"/>
      <node ref="D109" pin="3"/>
      <node ref="D110" pin="3"/>
      <node ref="D107" pin="3"/>
      <node ref="D106" pin="3"/>
      <node ref="U101" pin="26"/>
    </net>
    <net code="71" name="ROW0">
      <node ref="D102" pin="3"/>
      <node ref="U101" pin="32"/>
      <node ref="D101" pin="3"/>
      <node ref="D105" pin="3"/>
      <node ref="D104" pin="3"/>
      <node ref="D103" pin="3"/>
    </net>
    <net code="72" name="Net-(U101-Pad41)">
      <node ref="U101" pin="41"/>
    </net>
    <net code="73" name="Net-(U101-Pad42)">
      <node ref="U101" pin="42"/>
    </net>
    <net code="74" name="Net-(U101-Pad8)">
      <node ref="U101" pin="8"/>
    </net>
    <net code="75" name="Net-(U101-Pad9)">
      <node ref="U101" pin="9"/>
    </net>
    <net code="76" name="CC1">
      <node ref="R101" pin="2"/>
      <node ref="USB101" pin="4"/>
    </net>
    <net code="77" name="CC2">
      <node ref="R102" pin="1"/>
      <node ref="USB101" pin="10"/>
    </net>
    <net code="78" name="VBUS">
      <node ref="USB101" pin="11"/>
      <node ref="USB101" pin="2"/>
      <node ref="F101" pin="1"/>
    </net>
    <net code="79" name="Net-(USB101-Pad9)">
      <node ref="USB101" pin="9"/>
    </net>
    <net code="80" name="Net-(USB101-Pad3)">
      <node ref="USB101" pin="3"/>
    </net>
    <net code="81" name="Earth">
      <node ref="USB101" pin="1"/>
      <node ref="USB101" pin="12"/>
      <node ref="USB101" pin="13"/>
      <node ref="L101" pin="2"/>
    </net>
  </nets>
</export>
